chain_app_client_sdk/__init__.py
chain_app_client_sdk/api_client.py
chain_app_client_sdk/configuration.py
chain_app_client_sdk/exceptions.py
chain_app_client_sdk/rest.py
chain_app_client_sdk/schemas.py
chain_app_client_sdk/apis/__init__.py
chain_app_client_sdk/apis/path_to_api.py
chain_app_client_sdk/apis/tag_to_api.py
chain_app_client_sdk/apis/paths/__init__.py
chain_app_client_sdk/apis/paths/auth_signin.py
chain_app_client_sdk/apis/paths/auth_signup.py
chain_app_client_sdk/apis/paths/main_pool_actions_unstake_token.py
chain_app_client_sdk/apis/paths/main_pool_get_info.py
chain_app_client_sdk/apis/paths/main_pool_get_pool_size_history.py
chain_app_client_sdk/apis/paths/mass_claiming_get_claimable_bind.py
chain_app_client_sdk/apis/paths/mass_claiming_mass_claiming.py
chain_app_client_sdk/apis/paths/staking_on_behalf_stake.py
chain_app_client_sdk/apis/paths/user_info_get_locked_bind_by_user_id.py
chain_app_client_sdk/apis/paths/user_info_get_release_date_by_user_id.py
chain_app_client_sdk/apis/paths/user_info_get_staked_bind_by_user_id.py
chain_app_client_sdk/apis/paths/user_info_get_unstakable_bind_by_user_id.py
chain_app_client_sdk/apis/tags/__init__.py
chain_app_client_sdk/apis/tags/auth_api.py
chain_app_client_sdk/apis/tags/main_api.py
chain_app_client_sdk/apis/tags/main_pool_api.py
chain_app_client_sdk/apis/tags/mass_claiming_api.py
chain_app_client_sdk/apis/tags/user_info_api.py
chain_app_client_sdk/model/__init__.py
chain_app_client_sdk/model/get_claimable_bind_data_response.py
chain_app_client_sdk/model/get_claimable_bind_item_response.py
chain_app_client_sdk/model/get_claimable_bind_response.py
chain_app_client_sdk/model/get_release_date_by_user.py
chain_app_client_sdk/model/get_release_date_by_user_data.py
chain_app_client_sdk/model/locked_bind.py
chain_app_client_sdk/model/main_pool_info.py
chain_app_client_sdk/model/main_pool_info_data.py
chain_app_client_sdk/model/mass_claiming.py
chain_app_client_sdk/model/mass_claiming_response.py
chain_app_client_sdk-1.0.5.dist-info/METADATA
chain_app_client_sdk-1.0.5.dist-info/WHEEL
chain_app_client_sdk-1.0.5.dist-info/top_level.txt
chain_app_client_sdk-1.0.5.dist-info/RECORD
