Metadata-Version: 2.1
Name: chain-app-client-sdk
Version: 1.0.5
Summary: Chain App BIND client SDK
Home-page: UNKNOWN
Author: BIND Contact
Author-email: support@bind.com
License: MIT
Keywords: OpenAPI,OpenAPI-Generator,Chain App BIND client SDK
Platform: UNKNOWN
Requires-Python: >=3.7
Requires-Dist: certifi (>=14.5.14)
Requires-Dist: frozendict (~=2.3.4)
Requires-Dist: python-dateutil (~=2.7.0)
Requires-Dist: setuptools (>=21.0.0)
Requires-Dist: typing-extensions (~=4.3.0)
Requires-Dist: urllib3 (~=1.26.7)
